MANIFEST.in
README.md
license.txt
setup.py
taskr/__init__.py
taskr/argparser.py
taskr/taskr.py
taskr/terminal.py
taskr.egg-info/PKG-INFO
taskr.egg-info/SOURCES.txt
taskr.egg-info/dependency_links.txt
taskr.egg-info/requires.txt
taskr.egg-info/top_level.txt
taskr/contrib/__init__.py
taskr/contrib/cli.py
taskr/contrib/collections.py
taskr/contrib/converters.py
taskr/contrib/django.py
taskr/contrib/filetools.py
taskr/contrib/git.py
taskr/contrib/lang.py
taskr/contrib/net.py
taskr/contrib/plist.py
taskr/contrib/reader.py
taskr/contrib/validators.py
taskr/contrib/system/__init__.py
taskr/contrib/system/osx.py